ALU.v
module ALU(output reg [15:0]Result,output reg [5:0]Status,
            input [15:0] A,B,
            input [4:0] F,
            input Cin);
    // All functions Needed in ALU
    localparam   [4:0]
                INC = 5'b00001,
                DEC = 5'b00011,
                ADD = 5'b00100,
                ADD_CARRY = 5'b00101,
                SUB = 5'b00110,
                SUB_BORROW = 5'b00111,
                AND = 5'b01000,
                OR = 5'b01001,
                XOR = 5'b01010,
                NOT = 5'b01011,
                SHL = 5'b10000,
                SHR = 5'b10001,
                SAL = 5'b10010,
                SAR = 5'b10011,
                ROL = 5'b10100,
                ROR = 5'b10101,
                RCL = 5'b10110,
                RCR = 5'b10111;
    // FLags
    localparam  
                CARRY_F = 5,
                ZERO_F = 4,
                NEGATIVE_F = 3,
                OVERFLOW_F = 2,
                PARITY_F = 1,
                AUX_CARRY_F = 0;
    // Internal signals for AUX carry (SUB operations)
    wire [4:0] sub_aux = {1'b0, A[3:0]} - {1'b0, B[3:0]};
    wire [4:0] sub_borrow_aux = {1'b0, A[3:0]} - {1'b0, B[3:0]} - {4'b0, Cin};
    wire [4:0] dec_aux = {1'b0, A[3:0]} - 5'h1;
    
    // Internal signals for AUX carry (ADD operations)  
    wire [4:0] add_aux = {1'b0, A[3:0]} + {1'b0, B[3:0]};
    wire [4:0] add_carry_aux = {1'b0, A[3:0]} + {1'b0, B[3:0]} + {4'b0, Cin};
    wire [4:0] inc_aux = {1'b0, A[3:0]} + 5'h1;
    // Internal signals for arithmetic operations
    wire [16:0] add_result = A + B + ((F == ADD_CARRY) ? Cin : 1'b0);
    wire [16:0] sub_result = A - B - ((F == SUB_BORROW) ? Cin : 1'b0);
    wire [16:0] inc_result = A + 17'h00001;
    wire [16:0] dec_result = A - 17'h00001;
    // Result Setting
    always @(*) begin
        case (F)
            INC : Result = A + 16'h0001;
            DEC : Result = A - 16'h0001;
            ADD : Result = A + B;
            ADD_CARRY : Result = A + B + Cin;
            SUB : Result = A - B;
            SUB_BORROW : Result = A - B - Cin;
            AND : Result = A & B;
            OR : Result =  A | B;
            XOR : Result = A ^ B;
            NOT : Result = ~A;
            SHL : Result = A << 1;
            SHR : Result = A >> 1;
            SAL : Result = A <<< 1;
            SAR : Result = {A[15], A[15:1]};
            ROL : Result = {A[14:0],A[15]};
            ROR : Result = {A[0],A[15:1]};
            RCL : Result = {A[14:0],Cin};
            RCR : Result = {Cin,A[15:1]};
            default: Result = 16'h0000;
        endcase
    end
    // Status Setting
    always @(*) begin
        Status[ZERO_F] = (Result == 16'h0000);
        Status[NEGATIVE_F] = Result[15];              // MSB
        Status[PARITY_F] = ~(^Result);
        Status[CARRY_F] = 1'b0;
        Status[OVERFLOW_F] = 1'b0;
        Status[AUX_CARRY_F] = 1'b0;
        case (F)
            ADD,ADD_CARRY,SUB,SUB_BORROW,INC,DEC: begin
                // SUB Operation
                if(F[1]) begin
                    Status[CARRY_F] = (F == DEC) ? dec_result[16] : sub_result[16];
                    Status[OVERFLOW_F] = (A[15] != B[15]) && (Result[15] != A[15]);
                    case (F)
                        SUB:      Status[AUX_CARRY_F] = sub_aux[4];  // Borrow from nibble
                        SUB_BORROW: Status[AUX_CARRY_F] = sub_borrow_aux[4];
                        DEC:      Status[AUX_CARRY_F] = dec_aux[4];
                        default:  Status[AUX_CARRY_F] = 1'b0;
                    endcase
                end
                // ADD Operation
                else begin
                    Status[CARRY_F] = (F == INC) ? inc_result[16] : add_result[16];
                    Status[OVERFLOW_F] = (A[15] == B[15]) && (Result[15] != A[15]);
                    Status[AUX_CARRY_F] = (F == INC) ? inc_result[4] : add_result[4];
                end
            end
            ROL,RCL,SHL,SAL:begin
                Status[CARRY_F] = A[15];
            end
            ROR,RCR,SAR,SHR:begin
                Status[CARRY_F] = A[0];
            end
            default: begin
                Status[CARRY_F] = 1'b0;
                Status[OVERFLOW_F] = 1'b0;
                Status[AUX_CARRY_F] = 1'b0;
            end
        endcase
    end
endmodule

`timescale 1ps/1ps
module TB_ALU;
wire [15:0] Result;
wire [5:0] Status;
reg [15:0] A,B;
reg [4:0] F;
reg Cin;
ALU ALU_BlockTest (.Result(Result),.Status(Status),.A(A),.B(B),.F(F),.Cin(Cin));
initial begin
    #320 $finish;
end
initial begin
    $dumpfile("ALU_TESTBENCH.vcd");
    $dumpvars(0,TB_ALU);
end
initial fork 
    // operations
    #0 {A,B,F,Cin} = {16'h0000,16'h0000,5'b00000,1'b1};
    #10 {A,B,F,Cin} = {16'h0000,16'h0000,5'b00010,1'b1};
    #20 {A,B,F,Cin} = {16'h0000,16'h0000,5'b00001,1'b1};
    #30 {A,B,F,Cin} = {16'h0001,16'h0000,5'b00001,1'b1};
    #40 {A,B,F,Cin} = {16'h0001,16'h0000,5'b00011,1'b1};
    #50 {A,B,F,Cin} = {16'h0003,16'h0004,5'b00100,1'b1};
    #60 {A,B,F,Cin} = {16'h0003,16'h0004,5'b00101,1'b1};
    #70 {A,B,F,Cin} = {16'h0007,16'h0003,5'b00110,1'b1};
    #80 {A,B,F,Cin} = {16'h0007,16'h0003,5'b00111,1'b1};
    #90 {A,B,F,Cin} = {16'h0007,16'h0003,5'b01000,1'b1};
    #100 {A,B,F,Cin} = {16'h0007,16'h0003,5'b01001,1'b1};
    #110 {A,B,F,Cin} = {16'h0007,16'h0003,5'b01010,1'b1};
    #120 {A,B,F,Cin} = {16'h0007,16'h0003,5'b01011,1'b1};
    #130 {A,B,F,Cin} = {16'h80f0,16'h0003,5'b10000,1'b1};
    #140 {A,B,F,Cin} = {16'h0f0f,16'h0003,5'b10001,1'b1};
    #150 {A,B,F,Cin} = {16'hf0f0,16'h0003,5'b10010,1'b1};
    #160 {A,B,F,Cin} = {16'hf0f1,16'h0003,5'b10011,1'b1};
    #170 {A,B,F,Cin} = {16'hf0f0,16'h0003,5'b10100,1'b1};
    #180 {A,B,F,Cin} = {16'h0f0f,16'h0003,5'b10101,1'b1};
    #190 {A,B,F,Cin} = {16'h0f0f,16'h0003,5'b10110,1'b1};
    #200 {A,B,F,Cin} = {16'h3f00,16'h0003,5'b10111,1'b1};
    // Overflow FLag Testing
    #210 {A,B,F,Cin} = {16'h7fff,16'h0001,5'b00100,1'b1};
    #220 {A,B,F,Cin} = {16'h7fff,16'h0001,5'b00101,1'b1};
    #230 {A,B,F,Cin} = {16'h7fff,16'hffff,5'b00110,1'b1};
    #240 {A,B,F,Cin} = {16'h7fff,16'hfff5,5'b00111,1'b1};
    // aux.  flag testing
    #250 {A,B,F,Cin} = {16'h0012,16'h0005,5'b00110,1'b0};
    #260 {A,B,F,Cin} = {16'h0013,16'h0003,5'b00111,1'b1};
    #270 {A,B,F,Cin} = {16'h0010,16'h0000,5'b00011,1'b0};
    #280 {A,B,F,Cin} = {16'h0009,16'h0008,5'b00100,1'b0};
    #290 {A,B,F,Cin} = {16'h0008,16'h0008,5'b00101,1'b1};
    #300 {A,B,F,Cin} = {16'h000F,16'h0000,5'b00001,1'b0};
join
endmodule

ALU_TESTBENCH.vcd
$date
	Mon Nov 24 02:21:45 2025
$end
$version
	Icarus Verilog
$end
$timescale
	1ps
$end
$scope module TB_ALU $end
$var wire 6 ! Status [5:0] $end
$var wire 16 " Result [15:0] $end
$var reg 16 # A [15:0] $end
$var reg 16 $ B [15:0] $end
$var reg 1 % Cin $end
$var reg 5 & F [4:0] $end
$scope module ALU_BlockTest $end
$var wire 16 ' A [15:0] $end
$var wire 16 ( B [15:0] $end
$var wire 1 % Cin $end
$var wire 5 ) F [4:0] $end
$var wire 17 * sub_result [16:0] $end
$var wire 5 + sub_borrow_aux [4:0] $end
$var wire 5 , sub_aux [4:0] $end
$var wire 17 - inc_result [16:0] $end
$var wire 5 . inc_aux [4:0] $end
$var wire 17 / dec_result [16:0] $end
$var wire 5 0 dec_aux [4:0] $end
$var wire 17 1 add_result [16:0] $end
$var wire 5 2 add_carry_aux [4:0] $end
$var wire 5 3 add_aux [4:0] $end
$var parameter 5 4 ADD $end
$var parameter 5 5 ADD_CARRY $end
$var parameter 5 6 AND $end
$var parameter 32 7 AUX_CARRY_F $end
$var parameter 32 8 CARRY_F $end
$var parameter 5 9 DEC $end
$var parameter 5 : INC $end
$var parameter 32 ; NEGATIVE_F $end
$var parameter 5 < NOT $end
$var parameter 5 = OR $end
$var parameter 32 > OVERFLOW_F $end
$var parameter 32 ? PARITY_F $end
$var parameter 5 @ RCL $end
$var parameter 5 A RCR $end
$var parameter 5 B ROL $end
$var parameter 5 C ROR $end
$var parameter 5 D SAL $end
$var parameter 5 E SAR $end
$var parameter 5 F SHL $end
$var parameter 5 G SHR $end
$var parameter 5 H SUB $end
$var parameter 5 I SUB_BORROW $end
$var parameter 5 J XOR $end
$var parameter 32 K ZERO_F $end
$var reg 16 L Result [15:0] $end
$var reg 6 M Status [5:0] $end
$upscope $end
$upscope $end
$enddefinitions $end
$comment Show the parameter values. $end
$dumpall
b100 K
b1010 J
b111 I
b110 H
b10001 G
b10000 F
b10011 E
b10010 D
b10101 C
b10100 B
b10111 A
b10110 @
b1 ?
b10 >
b1001 =
b1011 <
b11 ;
b1 :
b11 9
b101 8
b0 7
b1000 6
b101 5
b100 4
$end
#0
$dumpvars
b10010 M
b0 L
b0 3
b1 2
b0 1
b11111 0
b11111111111111111 /
b1 .
b1 -
b0 ,
b11111 +
b0 *
b0 )
b0 (
b0 '
b0 &
1%
b0 $
b0 #
b0 "
b10010 !
$end
#10
b10 &
b10 )
#20
b0 !
b0 M
b1 "
b1 L
b1 &
b1 )
#30
b10 "
b10 L
b1 ,
b0 +
b0 0
b1 3
b10 2
b10 .
b1 1
b1 *
b10 -
b0 /
b1 #
b1 '
#40
b10010 !
b10010 M
b0 "
b0 L
b11 &
b11 )
#50
b10 0
b100 .
b11111 ,
b11110 +
b111 3
b1000 2
b0 !
b0 M
b111 "
b111 L
b100 -
b10 /
b11 #
b11 '
b111 1
b11111111111111111 *
b100 $
b100 (
b100 &
b100 )
#60
b1000 "
b1000 L
b1000 1
b101 &
b101 )
#70
b110 0
b1000 .
b100 ,
b11 +
b1010 3
b1011 2
b0 !
b0 M
b100 "
b100 L
b1000 -
b110 /
b111 #
b111 '
b1010 1
b100 *
b11 $
b11 (
b110 &
b110 )
#80
b10 !
b10 M
b11 "
b11 L
b11 *
b111 &
b111 )
#90
b100 *
b1000 &
b1000 )
#100
b0 !
b0 M
b111 "
b111 L
b1001 &
b1001 )
#110
b100 "
b100 L
b1010 &
b1010 )
#120
b1000 !
b1000 M
b1111111111111000 "
b1111111111111000 L
b1011 &
b1011 )
#130
b11101 ,
b11100 +
b11111 0
b11 3
b100 2
b1 .
b100010 !
b100010 M
b111100000 "
b111100000 L
b1000000011110011 1
b1000000011101101 *
b1000000011110001 -
b1000000011101111 /
b1000000011110000 #
b1000000011110000 '
b10000 &
b10000 )
#140
b1100 ,
b1011 +
b1110 0
b10010 3
b10011 2
b10000 .
b100000 !
b100000 M
b11110000111 "
b11110000111 L
b111100010010 1
b111100001100 *
b111100010000 -
b111100001110 /
b111100001111 #
b111100001111 '
b10001 &
b10001 )
#150
b11101 ,
b11100 +
b11111 0
b11 3
b100 2
b1 .
b101000 !
b101000 M
b1110000111100000 "
b1110000111100000 L
b1111000011110011 1
b1111000011101101 *
b1111000011110001 -
b1111000011101111 /
b1111000011110000 #
b1111000011110000 '
b10010 &
b10010 )
#160
b11110 ,
b11101 +
b0 0
b100 3
b101 2
b10 .
b101000 !
b101000 M
b1111100001111000 "
b1111100001111000 L
b1111000011110100 1
b1111000011101110 *
b1111000011110010 -
b1111000011110000 /
b1111000011110001 #
b1111000011110001 '
b10011 &
b10011 )
#170
b11101 ,
b11100 +
b11111 0
b11 3
b100 2
b1 .
b101010 !
b101010 M
b1110000111100001 "
b1110000111100001 L
b1111000011110011 1
b1111000011101101 *
b1111000011110001 -
b1111000011101111 /
b1111000011110000 #
b1111000011110000 '
b10100 &
b10100 )
#180
b1100 ,
b1011 +
b1110 0
b10010 3
b10011 2
b10000 .
b101010 !
b101010 M
b1000011110000111 "
b1000011110000111 L
b111100010010 1
b111100001100 *
b111100010000 -
b111100001110 /
b111100001111 #
b111100001111 '
b10101 &
b10101 )
#190
b0 !
b0 M
b1111000011111 "
b1111000011111 L
b10110 &
b10110 )
#200
b11101 ,
b11100 +
b11111 0
b11 3
b100 2
b1 .
b1000 !
b1000 M
b1001111110000000 "
b1001111110000000 L
b11111100000011 1
b11111011111101 *
b11111100000001 -
b11111011111111 /
b11111100000000 #
b11111100000000 '
b10111 &
b10111 )
#210
b1110 0
b10000 .
b1110 ,
b1101 +
b10000 3
b10001 2
b1100 !
b1100 M
b1000000000000000 "
b1000000000000000 L
b1000000000000000 -
b111111111111110 /
b111111111111111 #
b111111111111111 '
b1000000000000000 1
b111111111111110 *
b1 $
b1 (
b100 &
b100 )
#220
b1110 !
b1110 M
b1000000000000001 "
b1000000000000001 L
b1000000000000001 1
b101 &
b101 )
#230
b0 ,
b11111 +
b11110 3
b11111 2
b101100 !
b101100 M
b1000000000000000 "
b1000000000000000 L
b10111111111111110 1
b11000000000000000 *
b1111111111111111 $
b1111111111111111 (
b110 &
b110 )
#240
b1010 ,
b1001 +
b10100 3
b10101 2
b101100 !
b101100 M
b1000000000001001 "
b1000000000001001 L
b10111111111110100 1
b11000000000001001 *
b1111111111110101 $
b1111111111110101 (
b111 &
b111 )
#250
b11101 ,
b1 0
b111 3
b11 .
b1101 "
b1101 L
b1 !
b1 M
b10011 -
b10001 /
b10010 #
b10010 '
b10111 1
b1101 *
b101 $
b101 (
b110 &
b110 )
b11101 +
b111 2
0%
#260
b10 0
b100 .
b0 ,
b110 3
b1111 "
b1111 L
b11 !
b11 M
b10100 -
b10010 /
b10011 #
b10011 '
b10110 1
b1111 *
b11 $
b11 (
b111 &
b111 )
b11111 +
b111 2
1%
#270
b11111 0
b1 .
b0 ,
b0 3
b11 !
b11 M
b10001 -
b1111 /
b10000 #
b10000 '
b10000 1
b10000 *
b0 $
b0 (
b11 &
b11 )
b0 +
b0 2
0%
#280
b1000 0
b1010 .
b1 ,
b1 +
b10001 3
b10001 2
b11 !
b11 M
b10001 "
b10001 L
b1010 -
b1000 /
b1001 #
b1001 '
b10001 1
b1 *
b1000 $
b1000 (
b100 &
b100 )
#290
b0 ,
b111 0
b10000 3
b1001 .
b11 !
b11 M
b10001 1
b0 *
b1001 -
b111 /
b1000 #
b1000 '
b101 &
b101 )
b11111 +
b10001 2
1%
#300
b1110 0
b10000 .
b1111 ,
b1111 3
b10000 "
b10000 L
b1 !
b1 M
b10000 -
b1110 /
b1111 #
b1111 '
b1111 1
b1111 *
b0 $
b0 (
b1 &
b1 )
b1111 +
b1111 2
0%
