ALU.v
module ALU(output reg [15:0]Result,output reg [5:0]Status,
            input [15:0] A,B,
            input [4:0] F,
            input Cin);
    // All functions Needed in ALU
    localparam   [4:0]
                INC = 5'b00001,
                DEC = 5'b00011,
                ADD = 5'b00100,
                ADD_CARRY = 5'b00101,
                SUB = 5'b00110,
                SUB_BORROW = 5'b00111,
                AND = 5'b01000,
                OR = 5'b01001,
                XOR = 5'b01010,
                NOT = 5'b01011,
                SHL = 5'b10000,
                SHR = 5'b10001,
                SAL = 5'b10010,
                SAR = 5'b10011,
                ROL = 5'b10100,
                ROR = 5'b10101,
                RCL = 5'b10110,
                RCR = 5'b10111;
    // FLags
    localparam  
                CARRY_F = 5,
                ZERO_F = 4,
                NEGATIVE_F = 3,
                OVERFLOW_F = 2,
                PARITY_F = 1,
                AUX_CARRY_F = 0;
    // Internal signals for arithmetic operations
    wire [16:0] add_result = A + B + ((F == ADD_CARRY) ? Cin : 1'b0);
    wire [16:0] sub_result = A - B - ((F == SUB_BORROW) ? Cin : 1'b0);
    wire [16:0] inc_result = A + 17'h00001;
    wire [16:0] dec_result = A - 17'h00001;
    // Result Setting
    always @(*) begin
        case (F)
            INC : Result = A + 16'h0001;
            DEC : Result = A - 16'h0001;
            ADD : Result = A + B;
            ADD_CARRY : Result = A + B + Cin;
            SUB : Result = A - B;
            SUB_BORROW : Result = A - B - Cin;
            AND : Result = A & B;
            OR : Result =  A | B;
            XOR : Result = A ^ B;
            NOT : Result = ~A;
            SHL : Result = A << 1;
            SHR : Result = A >> 1;
            SAL : Result = A <<< 1;
            SAR : Result = {A[15], A[15:1]};
            ROL : Result = {A[14:0],A[15]};
            ROR : Result = {A[0],A[15:1]};
            RCL : Result = {A[14:0],Cin};
            RCR : Result = {Cin,A[15:1]};
            default: Result = 16'h0000;
        endcase
    end
    // Status Setting
    always @(*) begin
        Status[ZERO_F] = (Result == 16'h0000);
        Status[NEGATIVE_F] = Result[15];              // MSB
        Status[PARITY_F] = ~(^Result);
        Status[CARRY_F] = 1'b0;
        Status[OVERFLOW_F] = 1'b0;
        Status[AUX_CARRY_F] = 1'b0;
        case (F)
            ADD,ADD_CARRY,SUB,SUB_BORROW,INC,DEC: begin
                // SUB Operation
                if(F[1]) begin
                    Status[CARRY_F] = (F == DEC) ? dec_result[16] : sub_result[16];
                    Status[OVERFLOW_F] = (A[15] != B[15]) && (Result[15] != A[15]);
                    if(F != DEC) Status[AUX_CARRY_F] = (A[3:0] < B[3:0]);
                    else Status[AUX_CARRY_F] = (A[3:0] < (B[3:0] + Cin));
                end
                // ADD Operation
                else begin
                    Status[CARRY_F] = (F == INC) ? inc_result[16] : add_result[16];
                    Status[OVERFLOW_F] = (A[15] == B[15]) && (Result[15] != A[15]);
                    if(F != INC) Status[AUX_CARRY_F] = (A[3:0] + B[3:0] > 4'hF);
                    else Status[AUX_CARRY_F] = (A[3:0] + B[3:0] + Cin > 4'hF);
                end
            end
            ROL,RCL,SHL,SAL:begin
                Status[CARRY_F] = A[15];
            end
            ROR,RCR,SAR,SHR:begin
                Status[CARRY_F] = A[0];
            end
            default: begin
                Status[CARRY_F] = 1'b0;
                Status[OVERFLOW_F] = 1'b0;
                Status[AUX_CARRY_F] = 1'b0;
            end
        endcase
    end
endmodule

`timescale 1ps/1ps
module TB_ALU;
wire [15:0] Result;
wire [5:0] Status;
reg [15:0] A,B;
reg [4:0] F;
reg Cin;
ALU ALU_BlockTest (.Result(Result),.Status(Status),.A(A),.B(B),.F(F),.Cin(Cin));
initial begin
    #240 $finish;
end
initial begin
    $dumpfile("ALU_TESTBENCH.vcd");
    $dumpvars(0,TB_ALU);
end
initial fork 
    // operations
    #0 {A,B,F,Cin} = {16'h0000,16'h0000,5'b00000,1'b1};
    #10 {A,B,F,Cin} = {16'h0000,16'h0000,5'b00010,1'b1};
    #20 {A,B,F,Cin} = {16'h0000,16'h0000,5'b00001,1'b1};
    #30 {A,B,F,Cin} = {16'h0001,16'h0000,5'b00001,1'b1};
    #40 {A,B,F,Cin} = {16'h0001,16'h0000,5'b00011,1'b1};
    #50 {A,B,F,Cin} = {16'h0003,16'h0004,5'b00100,1'b1};
    #60 {A,B,F,Cin} = {16'h0003,16'h0004,5'b00101,1'b1};
    #70 {A,B,F,Cin} = {16'h0007,16'h0003,5'b00110,1'b1};
    #80 {A,B,F,Cin} = {16'h0007,16'h0003,5'b00111,1'b1};
    #90 {A,B,F,Cin} = {16'h0007,16'h0003,5'b01000,1'b1};
    #100 {A,B,F,Cin} = {16'h0007,16'h0003,5'b01001,1'b1};
    #110 {A,B,F,Cin} = {16'h0007,16'h0003,5'b01010,1'b1};
    #120 {A,B,F,Cin} = {16'h0007,16'h0003,5'b01011,1'b1};
    #130 {A,B,F,Cin} = {16'h80f0,16'h0003,5'b10000,1'b1};
    #140 {A,B,F,Cin} = {16'h0f0f,16'h0003,5'b10001,1'b1};
    #150 {A,B,F,Cin} = {16'hf0f0,16'h0003,5'b10010,1'b1};
    #160 {A,B,F,Cin} = {16'hf0f1,16'h0003,5'b10011,1'b1};
    #170 {A,B,F,Cin} = {16'hf0f0,16'h0003,5'b10100,1'b1};
    #180 {A,B,F,Cin} = {16'h0f0f,16'h0003,5'b10101,1'b1};
    #190 {A,B,F,Cin} = {16'h0f0f,16'h0003,5'b10110,1'b1};
    #200 {A,B,F,Cin} = {16'h3f00,16'h0003,5'b10111,1'b1};
    // FLags
join
endmodule

ALU_TESTBENCH.vcd
$date
	Mon Nov 24 00:07:58 2025
$end
$version
	Icarus Verilog
$end
$timescale
	1ps
$end
$scope module TB_ALU $end
$var wire 6 ! Status [5:0] $end
$var wire 16 " Result [15:0] $end
$var reg 16 # A [15:0] $end
$var reg 16 $ B [15:0] $end
$var reg 1 % Cin $end
$var reg 5 & F [4:0] $end
$scope module ALU_BlockTest $end
$var wire 16 ' A [15:0] $end
$var wire 16 ( B [15:0] $end
$var wire 1 % Cin $end
$var wire 5 ) F [4:0] $end
$var wire 17 * sub_result [16:0] $end
$var wire 17 + inc_result [16:0] $end
$var wire 17 , dec_result [16:0] $end
$var wire 17 - add_result [16:0] $end
$var parameter 5 . ADD $end
$var parameter 5 / ADD_CARRY $end
$var parameter 5 0 AND $end
$var parameter 32 1 AUX_CARRY_F $end
$var parameter 32 2 CARRY_F $end
$var parameter 5 3 DEC $end
$var parameter 5 4 INC $end
$var parameter 32 5 NEGATIVE_F $end
$var parameter 5 6 NOT $end
$var parameter 5 7 OR $end
$var parameter 32 8 OVERFLOW_F $end
$var parameter 32 9 PARITY_F $end
$var parameter 5 : RCL $end
$var parameter 5 ; RCR $end
$var parameter 5 < ROL $end
$var parameter 5 = ROR $end
$var parameter 5 > SAL $end
$var parameter 5 ? SAR $end
$var parameter 5 @ SHL $end
$var parameter 5 A SHR $end
$var parameter 5 B SUB $end
$var parameter 5 C SUB_BORROW $end
$var parameter 5 D XOR $end
$var parameter 32 E ZERO_F $end
$var reg 16 F Result [15:0] $end
$var reg 6 G Status [5:0] $end
$upscope $end
$upscope $end
$enddefinitions $end
$comment Show the parameter values. $end
$dumpall
b100 E
b1010 D
b111 C
b110 B
b10001 A
b10000 @
b10011 ?
b10010 >
b10101 =
b10100 <
b10111 ;
b10110 :
b1 9
b10 8
b1001 7
b1011 6
b11 5
b1 4
b11 3
b101 2
b0 1
b1000 0
b101 /
b100 .
$end
#0
$dumpvars
b10010 G
b0 F
b0 -
b11111111111111111 ,
b1 +
b0 *
b0 )
b0 (
b0 '
b0 &
1%
b0 $
b0 #
b0 "
b10010 !
$end
#10
b10 &
b10 )
#20
b0 !
b0 G
b1 "
b1 F
b1 &
b1 )
#30
b10 "
b10 F
b1 -
b1 *
b10 +
b0 ,
b1 #
b1 '
#40
b10010 !
b10010 G
b0 "
b0 F
b11 &
b11 )
#50
b0 !
b0 G
b111 "
b111 F
b100 +
b10 ,
b11 #
b11 '
b111 -
b11111111111111111 *
b100 $
b100 (
b100 &
b100 )
#60
b1000 "
b1000 F
b1000 -
b101 &
b101 )
#70
b100 "
b100 F
b1000 +
b110 ,
b111 #
b111 '
b1010 -
b100 *
b11 $
b11 (
b110 &
b110 )
#80
b10 !
b10 G
b11 "
b11 F
b11 *
b111 &
b111 )
#90
b100 *
b1000 &
b1000 )
#100
b0 !
b0 G
b111 "
b111 F
b1001 &
b1001 )
#110
b100 "
b100 F
b1010 &
b1010 )
#120
b1000 !
b1000 G
b1111111111111000 "
b1111111111111000 F
b1011 &
b1011 )
#130
b100010 !
b100010 G
b111100000 "
b111100000 F
b1000000011110011 -
b1000000011101101 *
b1000000011110001 +
b1000000011101111 ,
b1000000011110000 #
b1000000011110000 '
b10000 &
b10000 )
#140
b100000 !
b100000 G
b11110000111 "
b11110000111 F
b111100010010 -
b111100001100 *
b111100010000 +
b111100001110 ,
b111100001111 #
b111100001111 '
b10001 &
b10001 )
#150
b101000 !
b101000 G
b1110000111100000 "
b1110000111100000 F
b1111000011110011 -
b1111000011101101 *
b1111000011110001 +
b1111000011101111 ,
b1111000011110000 #
b1111000011110000 '
b10010 &
b10010 )
#160
b101000 !
b101000 G
b1111100001111000 "
b1111100001111000 F
b1111000011110100 -
b1111000011101110 *
b1111000011110010 +
b1111000011110000 ,
b1111000011110001 #
b1111000011110001 '
b10011 &
b10011 )
#170
b101010 !
b101010 G
b1110000111100001 "
b1110000111100001 F
b1111000011110011 -
b1111000011101101 *
b1111000011110001 +
b1111000011101111 ,
b1111000011110000 #
b1111000011110000 '
b10100 &
b10100 )
#180
b101010 !
b101010 G
b1000011110000111 "
b1000011110000111 F
b111100010010 -
b111100001100 *
b111100010000 +
b111100001110 ,
b111100001111 #
b111100001111 '
b10101 &
b10101 )
#190
b0 !
b0 G
b1111000011111 "
b1111000011111 F
b10110 &
b10110 )
#200
b1000 !
b1000 G
b1001111110000000 "
b1001111110000000 F
b11111100000011 -
b11111011111101 *
b11111100000001 +
b11111011111111 ,
b11111100000000 #
b11111100000000 '
b10111 &
b10111 )
